Metadata-Version: 2.1
Name: django-video-encoding-updated
Version: 1.0.0
Summary: django-video-encoding helps to convert your videos into different formats and resolutions.
Home-page: https://github.com/escaped/django-video-encoding
License: BSD-3-Clause
Author: Alexander Frenzel
Author-email: alex@relatedworks.com
Requires-Python: >=3.6.1,<4.0
Classifier: Development Status :: 4 - Beta
Classifier: Environment :: Web Environment
Classifier: Framework :: Django
Classifier: Intended Audience :: Developers
Classifier: License :: OSI Approved :: BSD License
Classifier: Operating System :: OS Independent
Classifier: Programming Language :: Python
Classifier: Programming Language :: Python :: 3
Classifier: Programming Language :: Python :: 3.10
Classifier: Programming Language :: Python :: 3.6
Classifier: Programming Language :: Python :: 3.7
Classifier: Programming Language :: Python :: 3.8
Classifier: Programming Language :: Python :: 3.9
Classifier: Topic :: Software Development :: Libraries :: Python Modules
Requires-Dist: django (>=2.2)
Requires-Dist: django-appconf (>=1.0,<2.0)
Requires-Dist: pillow (>=5.0)
Project-URL: Documentation, https://github.com/escaped/django-video-encoding/blob/master/README.md
Project-URL: Repository, https://github.com/escaped/django-video-encoding
